Metadata-Version: 2.1
Name: djangocms-modules
Version: 2.0.0
Summary: Adds copy/paste capabilities to groups of plugins
Home-page: https://github.com/django-cms/djangocms-modules
Author: Divio AG
Author-email: info@divio.ch
Maintainer: Django CMS Association and contributors
Maintainer-email: info@django-cms.org
License: BSD-3-Clause
Classifier: Development Status :: 5 - Production/Stable
Classifier: Environment :: Web Environment
Classifier: Intended Audience :: Developers
Classifier: License :: OSI Approved :: BSD License
Classifier: Operating System :: OS Independent
Classifier: Programming Language :: Python
Classifier: Programming Language :: Python :: 3
Classifier: Programming Language :: Python :: 3.8
Classifier: Programming Language :: Python :: 3.9
Classifier: Programming Language :: Python :: 3.10
Classifier: Framework :: Django
Classifier: Framework :: Django :: 3.2
Classifier: Framework :: Django :: 4.0
Classifier: Framework :: Django CMS
Classifier: Framework :: Django CMS :: 3.10
Classifier: Framework :: Django CMS :: 3.11
Classifier: Topic :: Internet :: WWW/HTTP
Classifier: Topic :: Internet :: WWW/HTTP :: Dynamic Content
Classifier: Topic :: Software Development
Classifier: Topic :: Software Development :: Libraries
Requires-Python: >=3.8
License-File: LICENSE
Requires-Dist: django-cms (>=3.7)
Requires-Dist: djangocms-history
Requires-Dist: django-treebeard (<4.5,>=4.3)
